README.rst
setup.py
peek_plugin_diagram_generic_menu/__init__.py
peek_plugin_diagram_generic_menu/plugin_package.json
peek_plugin_diagram_generic_menu.egg-info/PKG-INFO
peek_plugin_diagram_generic_menu.egg-info/SOURCES.txt
peek_plugin_diagram_generic_menu.egg-info/dependency_links.txt
peek_plugin_diagram_generic_menu.egg-info/requires.txt
peek_plugin_diagram_generic_menu.egg-info/top_level.txt
peek_plugin_diagram_generic_menu/_private/PluginNames.py
peek_plugin_diagram_generic_menu/_private/__init__.py
peek_plugin_diagram_generic_menu/_private/alembic.ini
peek_plugin_diagram_generic_menu/_private/admin-app/diagramGenericMenu.component.html
peek_plugin_diagram_generic_menu/_private/admin-app/diagramGenericMenu.component.ts
peek_plugin_diagram_generic_menu/_private/admin-app/diagramGenericMenu.module.ts
peek_plugin_diagram_generic_menu/_private/admin-app/edit-diagram-generic-menu-table/edit.component.html
peek_plugin_diagram_generic_menu/_private/admin-app/edit-diagram-generic-menu-table/edit.component.ts
peek_plugin_diagram_generic_menu/_private/admin-app/edit-setting-table/edit.component.html
peek_plugin_diagram_generic_menu/_private/admin-app/edit-setting-table/edit.component.ts
peek_plugin_diagram_generic_menu/_private/alembic/__init__.py
peek_plugin_diagram_generic_menu/_private/alembic/env.py
peek_plugin_diagram_generic_menu/_private/alembic/script.py.mako
peek_plugin_diagram_generic_menu/_private/alembic/versions/1f288982a4e2_initial.py
peek_plugin_diagram_generic_menu/_private/alembic/versions/__init__.py
peek_plugin_diagram_generic_menu/_private/alembic/versions/bac1e4f7a3d9_renamed_diagramgeneric_table.py
peek_plugin_diagram_generic_menu/_private/client/ClientEntryHook.py
peek_plugin_diagram_generic_menu/_private/client/DeviceTupleDataObservableProxy.py
peek_plugin_diagram_generic_menu/_private/client/DeviceTupleProcessorActionProxy.py
peek_plugin_diagram_generic_menu/_private/client/__init__.py
peek_plugin_diagram_generic_menu/_private/server/DiagramGenericMenuApi.py
peek_plugin_diagram_generic_menu/_private/server/ServerEntryHook.py
peek_plugin_diagram_generic_menu/_private/server/TupleActionProcessor.py
peek_plugin_diagram_generic_menu/_private/server/TupleDataObservable.py
