Metadata-Version: 1.1
Name: peek-plugin-diagram-generic-menu
Version: 1.3.10
Summary: Peek Plugin DiagramGenericMenu - My first enhancement.
Home-page: https://bitbucket.org/synerty/peek-plugin-diagram-generic-menu
Author: Synerty
Author-email: contact@synerty.com
License: UNKNOWN
Download-URL: https://bitbucket.org/synerty/peek-plugin-diagram-generic-menu/get/1.3.10.zip
Keywords: Peek,Python,Platform,synerty
Platform: UNKNOWN
